{
  "common": {
    "guest": "Khách",
    "loading": "Đang tải hồ sơ...",
    "waiting": "Đang chờ...",
    "orLeaveGuest": "Hoặc để là Khách",
    "win": "THẮNG",
    "loss": "THUA",
    "singles": "Đánh Đơn",
    "doubles": "Đánh Đôi",
    "rating": "Hệ số"
  },
  "sidebar": {
    "dashboard": "Dashboard",
    "logMatch": "Ghi Trận Đấu",
    "friends": "Bạn Bè",
    "events": "Sự Kiện",
    "hostEvent": "Tổ Chức Sự Kiện",
    "signOut": "Thoát",
    "language": "Ngôn Ngữ"
  },
  "dashboard": {
    "title": "Dashboard",
    "welcome": "Chào mừng!",
    "officialRating": "Hệ số DUPR Chính Thức",
    "recentForm": "Trận Gần Đây",
    "noSingles": "Chưa có lịch sử Đánh Đơn.",
    "noDoubles": "Chưa có lịch sử Đánh Đôi."
  },
  "friends": {
    "title": "Bạn Bè",
    "searchPlaceholder": "Nhập email của bạn bè...",
    "addBtn": "Thêm Bạn",
    "myFriends": "Danh Sách Bạn Bè",
    "noFriends": "Bạn chưa thêm ai vào danh sách.",
    "viewProfile": "Xem Hồ Sơ & Lịch Sử →"
  },
  "logMatch": {
    "manual": "Nhập Thủ Công",
    "host": "Tạo Phòng Live",
    "join": "Vào Phòng Live",
    "yourTeam": "Đội Của Bạn",
    "opponents": "Đối Thủ",
    "player1": "Người chơi 1",
    "partner": "Đồng đội",
    "opponent1": "Đối thủ 1",
    "opponent2": "Đối thủ 2",
    "scoreA": "Điểm Đội A",
    "scoreB": "Điểm Đội B",
    "submit": "Xác Nhận Kết Quả",
    "startLive": "Bắt Đầu Trận Live",
    "generatePin": "Tạo Mã Phòng",
    "matchPin": "MÃ PHÒNG TRẬN ĐẤU",
    "teamA": "Đội A",
    "teamB": "Đội B",
    "hostRole": "Chủ Phòng",
    "p1Role": "Người chơi 1",
    "p2Role": "Người chơi 2",
    "unfilled": "Các vị trí trống sẽ được ghi là Khách ẩn danh.",
    "joinLive": "Tham Gia Trận Live",
    "findMatch": "Tìm Trận",
    "chooseTeam": "Chọn Đội Của Bạn",
    "selectPosition": "Chọn một vị trí trống cho trận 2v2 này.",
    "taken": "Đã Chọn",
    "joinBtn": "Tham Gia →",
    "cancel": "Hủy",
    "youAreIn": "Bạn đã vào phòng!"
  },
  "profile": {
    "profileId": "ID Hồ Sơ",
    "duprRating": "Điểm DUPR",
    "onFriendsList": "✓ Đã Kết Bạn",
    "addFriend": "➕ Thêm Bạn",
    "totalMatches": "Tổng Số Trận",
    "wins": "Thắng",
    "losses": "Thua",
    "friendsRoster": "Danh Sách Bạn Bè",
    "loginToAdd": "Đăng nhập để thêm bạn!",
    "friendAdded": "Đã thêm vào danh sách bạn bè!",
    "noSingles": "Chưa có lịch sử Đánh Đơn.",
    "noDoubles": "Chưa có lịch sử Đánh Đôi."
  },
  "events": {
    "list": {
      "title": "Sự Kiện Nổi Bật",
      "currentRating": "Hệ số hiện tại của bạn:",
      "searchLabel": "Tìm Sự Kiện",
      "searchPlaceholder": "vd: Khai mạc sáng thứ Bảy...",
      "regionLabel": "Khu Vực",
      "regionPlaceholder": "vd: Hồ Chí Minh, VN",
      "duprLabel": "DUPR Của Tôi",
      "duprPlaceholder": "vd: 3.5",
      "noEvents": "Không tìm thấy sự kiện nào phù hợp với tiêu chí của bạn."
    },
    "status": {
      "completed": "Đã Kết Thúc",
      "live": "Đang Diễn Ra",
      "registration": "Mở Đăng Ký",
      "upcoming": "Sắp Tới",
      "tournament": "Giải Đấu",
      "open_play": "Đánh Mở"
    },
    "buttons": {
      "processing": "Đang Xử Lý...",
      "registered": "✓ Đã Đăng Ký",
      "pending_approval": "⏳ Đang Chờ Duyệt",
      "join_event": "Tham Gia Sự Kiện",
      "view_details": "Xem Chi Tiết",
      "event_completed": "Sự Kiện Đã Kết Thúc",
      "registration_closed": "Đóng Đăng Ký",
      "approve": "Duyệt",
      "reject": "Từ Chối",
      "lock_seeding": "Khóa Hạt Giống",
      "open_manager": "Mở Bảng Điều Khiển Quản Lý"
    },
    "tabs": {
      "overview": "Tổng Quan",
      "participants": "Người Tham Gia",
      "bracket": "🏆 Lịch Sử Nhánh Đấu",
      "admin": "⚙️ Quản Lý Admin"
    },
    "details": {
      "title": "Chi Tiết Sự Kiện",
      "welcome": "Chào mừng đến với sự kiện.",
      "bracket_note": "Lưu ý: Nếu số lượng người chơi không chẵn khi tạo nhánh đấu, các người chơi hạt giống cao nhất sẽ tự động nhận được 'Bye' (đặc cách vào Vòng 2) dựa trên hệ thống tự động.",
      "no_players": "Chưa có người chơi được duyệt.",
      "pending_title": "Đang Chờ Duyệt",
      "pending_desc": "Xác minh thanh toán ngoài nền tảng hoặc duyệt thủ công người chơi trước khi cho phép họ vào nhánh đấu chính thức.",
      "no_pending": "Hoàn tất! Không có yêu cầu đang chờ.",
      "manage_seeds_title": "Quản Lý Hạt Giống & Khóa Sự Kiện",
      "manage_seeds_desc": "Kéo và thả các thẻ bên dưới để điều chỉnh hạt giống thủ công."
    },
    "create": {
      "title": "Tổ Chức Sự Kiện Mới",
      "event_title": "Tên Sự Kiện",
      "titlePlaceholder": "vd: Khai mạc sáng thứ Bảy",
      "event_type": "Loại Sự Kiện",
      "type_tournament": "Giải Đấu (Có Nhánh Đấu)",
      "type_open": "Đánh Mở (Không Có Nhánh Đấu)",
      "format": "Thể Thức",
      "singles": "Đánh Đơn",
      "doubles": "Đánh Đôi",
      "begin_date": "Ngày Bắt Đầu",
      "end_date": "Ngày Kết Thúc",
      "region": "Khu Vực",
      "regionPlaceholder": "vd: Hồ Chí Minh, VN",
      "location": "Địa Điểm",
      "locationPlaceholder": "vd: Sân Hoàng Văn Thụ",
      "min_dupr": "DUPR Tối Thiểu",
      "max_dupr": "DUPR Tối Đa",
      "max_players": "Số Người Tối Đa",
      "publish_btn": "Đăng Sự Kiện",
      "error_even_players": "Số lượng người chơi tối đa phải là số chẵn!"
    }
  }
}